Problem 2/src/traffic_light.v
// Problem 2: Traffic Light Controller (Verilog-2001, no SystemVerilog)

module traffic_light #(
    parameter CLK_FREQ_HZ = 100_000_000, // board clock
    parameter TICK_HZ     = 1,           // tick frequency
    // Durations in ticks (not seconds)
    parameter A_GREEN_T   = 3,
    parameter A_YELLOW_T  = 2,
    parameter B_GREEN_T   = 3,
    parameter B_YELLOW_T  = 1,
    parameter W_GREEN_T   = 2,
    parameter W_RFLASH_T  = 2,
    parameter W_RSOLID_T  = 9
)(
    input  wire clk,
    input  wire reset,   // async active-high
    input  wire MAINT,
    output reg Ga, Ya, Ra,
    output reg Gb, Yb, Rb,
    output reg Gw, Rw
);

    // Tick generator
    localparam DIVISOR = CLK_FREQ_HZ / TICK_HZ;
    reg [31:0] div_cnt = 0;
    reg tick = 0;

    always @(posedge clk or posedge reset) begin
        if (reset) begin
            div_cnt <= 0;
            tick    <= 0;
        end else begin
            if (div_cnt == DIVISOR-1) begin
                div_cnt <= 0;
                tick    <= 1;
            end else begin
                div_cnt <= div_cnt + 1;
                tick    <= 0;
            end
        end
    end

    // Flash generator (approx 1Hz for maintenance, 2Hz for pedestrian flash)
    reg [7:0] flash_cnt = 0;
    reg flash = 0;
    always @(posedge clk or posedge reset) begin
        if (reset) begin
            flash_cnt <= 0;
            flash <= 0;
        end else if (tick) begin
            flash_cnt <= flash_cnt + 1;
            if (flash_cnt >= 1) begin
                flash <= ~flash;
                flash_cnt <= 0;
            end
        end
    end

    // FSM states (localparams instead of typedef)
    localparam S_A_G      = 3'd0,
               S_A_Y      = 3'd1,
               S_B_G      = 3'd2,
               S_B_Y      = 3'd3,
               S_W_G      = 3'd4,
               S_W_RFLASH = 3'd5,
               S_W_RSOLID = 3'd6,
               S_MAINT    = 3'd7;

    reg [2:0] state, next_state;
    reg [15:0] tcnt;

    // State register
    always @(posedge clk or posedge reset) begin
        if (reset) begin
            state <= S_A_G;
            tcnt <= 0;
        end else if (tick) begin
            state <= next_state;
            if (state == next_state)
                tcnt <= tcnt + 1;
            else
                tcnt <= 0;
        end
    end

    // Next-state logic
    always @(*) begin
        if (MAINT) begin
            next_state = S_MAINT;
        end else begin
            case (state)
                S_A_G:       next_state = (tcnt >= A_GREEN_T-1)  ? S_A_Y      : S_A_G;
                S_A_Y:       next_state = (tcnt >= A_YELLOW_T-1) ? S_B_G      : S_A_Y;
                S_B_G:       next_state = (tcnt >= B_GREEN_T-1)  ? S_B_Y      : S_B_G;
                S_B_Y:       next_state = (tcnt >= B_YELLOW_T-1) ? S_W_G      : S_B_Y;
                S_W_G:       next_state = (tcnt >= W_GREEN_T-1)  ? S_W_RFLASH : S_W_G;
                S_W_RFLASH:  next_state = (tcnt >= W_RFLASH_T-1) ? S_W_RSOLID : S_W_RFLASH;
                S_W_RSOLID:  next_state = (tcnt >= W_RSOLID_T-1) ? S_A_G      : S_W_RSOLID;
                S_MAINT:     next_state = (MAINT ? S_MAINT : S_A_G);
                default:     next_state = S_A_G;
            endcase
        end
    end

    // Output logic
    always @(*) begin
        // defaults off
        Ga=0; Ya=0; Ra=0;
        Gb=0; Yb=0; Rb=0;
        Gw=0; Rw=0;

        if (MAINT) begin
            Ra = flash;
            Rb = flash;
            Rw = flash;
        end else begin
            case (state)
                S_A_G:      begin Ga=1; Rb=1; Rw=1; end
                S_A_Y:      begin Ya=1; Rb=1; Rw=1; end
                S_B_G:      begin Ra=1; Gb=1; Rw=1; end
                S_B_Y:      begin Ra=1; Yb=1; Rw=1; end
                S_W_G:      begin Ra=1; Rb=1; Gw=1; end
                S_W_RFLASH: begin Ra=1; Rb=1; Rw=flash; end
                S_W_RSOLID: begin Ra=1; Rb=1; Rw=1; end
                default:    ;
            endcase
        end
    end

endmodule

Problem 2/tb/tb_traffic_light.v
`timescale 1ns/1ps

module tb_traffic_light;
    reg clk, reset, MAINT;
    wire Ga, Ya, Ra, Gb, Yb, Rb, Gw, Rw;

    // Simulation parameters (faster for testing)
    parameter SIM_CLK_FREQ = 1_000_000;  // 1 MHz
    parameter SIM_TICK_HZ  = 1000;       // 1 kHz tick

    traffic_light #(
        .CLK_FREQ_HZ(SIM_CLK_FREQ),
        .TICK_HZ(SIM_TICK_HZ),
        .A_GREEN_T(3),
        .A_YELLOW_T(2),
        .B_GREEN_T(3),
        .B_YELLOW_T(1),
        .W_GREEN_T(2),
        .W_RFLASH_T(2),
        .W_RSOLID_T(5)
    ) dut (
        .clk(clk), .reset(reset), .MAINT(MAINT),
        .Ga(Ga), .Ya(Ya), .Ra(Ra),
        .Gb(Gb), .Yb(Yb), .Rb(Rb),
        .Gw(Gw), .Rw(Rw)
    );

    // Clock generation
    initial clk = 0;
    always #0.5 clk = ~clk;  // 1 MHz -> 1 us period

    initial begin
        $dumpfile("tb_traffic_light.vcd");
        $dumpvars(0, tb_traffic_light);

        // Init
        reset = 1; MAINT = 0;
        #5 reset = 0;

        // Normal sequence
        #5000;

        // Maintenance mode
        MAINT = 1;
        #2000;
        MAINT = 0;

        // Back to normal
        #5000;

        $finish;
    end

    initial begin
        $monitor("t=%0t | Ga=%b Ya=%b Ra=%b | Gb=%b Yb=%b Rb=%b | Gw=%b Rw=%b | MAINT=%b",
                  $time, Ga,Ya,Ra, Gb,Yb,Rb, Gw,Rw, MAINT);
    end
endmodule

project_3_pbm2/project_3_pbm2.sim/sim_1/behav/xsim/tb_traffic_light.vcd
$date
   Fri Oct 10 13:54:15 2025
$end

$version
  2025.1.0
  $dumpfile ("tb_traffic_light.vcd") 
$end

$timescale
  1ps
$end

$scope module tb_traffic_light $end
$var reg 1 ! clk $end
$var reg 1 " reset $end
$var reg 1 # MAINT $end
$var wire 1 $ Ga $end
$var wire 1 % Ya $end
$var wire 1 & Ra $end
$var wire 1 ' Gb $end
$var wire 1 ( Yb $end
$var wire 1 ) Rb $end
$var wire 1 * Gw $end
$var wire 1 + Rw $end
$scope module dut $end
$var wire 1 , clk $end
$var wire 1 - reset $end
$var wire 1 . MAINT $end
$var reg 1 / Ga $end
$var reg 1 0 Ya $end
$var reg 1 1 Ra $end
$var reg 1 2 Gb $end
$var reg 1 3 Yb $end
$var reg 1 4 Rb $end
$var reg 1 5 Gw $end
$var reg 1 6 Rw $end
$var reg 32 7 div_cnt [31:0] $end
$var reg 1 8 tick $end
$var reg 8 9 flash_cnt [7:0] $end
$var reg 1 : flash $end
$var reg 3 ; state [2:0] $end
$var reg 3 < next_state [2:0] $end
$var reg 16 = tcnt [15:0] $end
$upscope $end
$upscope $end
$enddefinitions $end

#0
$dumpvars
0!
1"
0#
1$
0%
0&
0'
0(
1)
0*
1+
0,
1-
0.
1/
00
01
02
03
14
05
16
b0 7
08
b0 9
0:
b0 ;
b0 <
b0 =
$end

#500
1!
1,

#1000
0!
0,

#1500
1!
1,

#2000
0!
0,

#2500
1!
1,

#3000
0!
0,

#3500
1!
1,

#4000
0!
0,

#4500
1!
1,

#5000
0!
0"
0,
0-

#5500
1!
1,
b1 7

#6000
0!
0,

#6500
1!
1,
b10 7

#7000
0!
0,

#7500
1!
1,
b11 7

#8000
0!
0,

#8500
1!
1,
b100 7

#9000
0!
0,

#9500
1!
1,
b101 7

#10000
0!
0,

#10500
1!
1,
b110 7

#11000
0!
0,

#11500
1!
1,
b111 7

#12000
0!
0,

#12500
1!
1,
b1000 7

#13000
0!
0,

#13500
1!
1,
b1001 7

#14000
0!
0,

#14500
1!
1,
b1010 7

#15000
0!
0,

#15500
1!
1,
b1011 7

#16000
0!
0,

#16500
1!
1,
b1100 7

#17000
0!
0,

#17500
1!
1,
b1101 7

#18000
0!
0,

#18500
1!
1,
b1110 7

#19000
0!
0,

#19500
1!
1,
b1111 7

#20000
0!
0,

#20500
1!
1,
b10000 7

#21000
0!
0,

#21500
1!
1,
b10001 7

#22000
0!
0,

#22500
1!
1,
b10010 7

#23000
0!
0,

#23500
1!
1,
b10011 7

#24000
0!
0,

#24500
1!
1,
b10100 7

#25000
0!
0,

#25500
1!
1,
b10101 7

#26000
0!
0,

#26500
1!
1,
b10110 7

#27000
0!
0,

#27500
1!
1,
b10111 7

#28000
0!
0,

#28500
1!
1,
b11000 7

#29000
0!
0,

#29500
1!
1,
b11001 7

#30000
0!
0,

#30500
1!
1,
b11010 7

#31000
0!
0,

#31500
1!
1,
b11011 7

#32000
0!
0,

#32500
1!
1,
b11100 7

#33000
0!
0,

#33500
1!
1,
b11101 7

#34000
0!
0,

#34500
1!
1,
b11110 7

#35000
0!
0,

#35500
1!
1,
b11111 7

#36000
0!
0,

#36500
1!
1,
b100000 7

#37000
0!
0,

#37500
1!
1,
b100001 7

#38000
0!
0,

#38500
1!
1,
b100010 7

#39000
0!
0,

#39500
1!
1,
b100011 7

#40000
0!
0,

#40500
1!
1,
b100100 7

#41000
0!
0,

#41500
1!
1,
b100101 7

#42000
0!
0,

#42500
1!
1,
b100110 7

#43000
0!
0,

#43500
1!
1,
b100111 7

#44000
0!
0,

#44500
1!
1,
b101000 7

#45000
0!
0,

#45500
1!
1,
b101001 7

#46000
0!
0,

#46500
1!
1,
b101010 7

#47000
0!
0,

#47500
1!
1,
b101011 7

#48000
0!
0,

#48500
1!
1,
b101100 7

#49000
0!
0,

#49500
1!
1,
b101101 7

#50000
0!
0,

#50500
1!
1,
b101110 7

#51000
0!
0,

#51500
1!
1,
b101111 7

#52000
0!
0,

#52500
1!
1,
b110000 7

#53000
0!
0,

#53500
1!
1,
b110001 7

#54000
0!
0,

#54500
1!
1,
b110010 7

#55000
0!
0,

#55500
1!
1,
b110011 7

#56000
0!
0,

#56500
1!
1,
b110100 7

#57000
0!
0,

#57500
1!
1,
b110101 7

#58000
0!
0,

#58500
1!
1,
b110110 7

#59000
0!
0,

#59500
1!
1,
b110111 7

#60000
0!
0,

#60500
1!
1,
b111000 7

#61000
0!
0,

#61500
1!
1,
b111001 7

#62000
0!
0,

#62500
1!
1,
b111010 7

#63000
0!
0,

#63500
1!
1,
b111011 7

#64000
0!
0,

#64500
1!
1,
b111100 7

#65000
0!
0,

#65500
1!
1,
b111101 7

#66000
0!
0,

#66500
1!
1,
b111110 7

#67000
0!
0,

#67500
1!
1,
b111111 7

#68000
0!
0,

#68500
1!
1,
b1000000 7

#69000
0!
0,

#69500
1!
1,
b1000001 7

#70000
0!
0,

#70500
1!
1,
b1000010 7

#71000
0!
0,

#71500
1!
1,
b1000011 7

#72000
0!
0,

#72500
1!
1,
b1000100 7

#73000
0!
0,

#73500
1!
1,
b1000101 7

#74000
0!
0,

#74500
1!
1,
b1000110 7

#75000
0!
0,

#75500
1!
1,
b1000111 7

#76000
0!
0,

#76500
1!
1,
b1001000 7

#77000
0!
0,

#77500
1!
1,
b1001001 7

#78000
0!
0,

#78500
1!
1,
b1001010 7

#79000
0!
0,

#79500
1!
1,
b1001011 7

#80000
0!
0,

#80500
1!
1,
b1001100 7

#81000
0!
0,

#81500
1!
1,
b1001101 7

#82000
0!
0,

#82500
1!
1,
b1001110 7

#83000
0!
0,

#83500
1!
1,
b1001111 7

#84000
0!
0,

#84500
1!
1,
b1010000 7

#85000
0!
0,

#85500
1!
1,
b1010001 7

#86000
0!
0,

#86500
1!
1,
b1010010 7

#87000
0!
0,

#87500
1!
1,
b1010011 7

#88000
0!
0,

#88500
1!
1,
b1010100 7

#89000
0!
0,

#89500
1!
1,
b1010101 7

#90000
0!
0,

#90500
1!
1,
b1010110 7

#91000
0!
0,

#91500
1!
1,
b1010111 7

#92000
0!
0,

#92500
1!
1,
b1011000 7

#93000
0!
0,

#93500
1!
1,
b1011001 7

#94000
0!
0,

#94500
1!
1,
b1011010 7

#95000
0!
0,

#95500
1!
1,
b1011011 7

#96000
0!
0,

#96500
1!
1,
b1011100 7

#97000
0!
0,

#97500
1!
1,
b1011101 7

#98000
0!
0,

#98500
1!
1,
b1011110 7

#99000
0!
0,

#99500
1!
1,
b1011111 7

#100000
0!
0,

#100500
1!
1,
b1100000 7

#101000
0!
0,

#101500
1!
1,
b1100001 7

#102000
0!
0,

#102500
1!
1,
b1100010 7

#103000
0!
0,

#103500
1!
1,
b1100011 7

#104000
0!
0,

#104500
1!
1,
b1100100 7

#105000
0!
0,

#105500
1!
1,
b1100101 7

#106000
0!
0,

#106500
1!
1,
b1100110 7

#107000
0!
0,

#107500
1!
1,
b1100111 7

#108000
0!
0,

#108500
1!
1,
b1101000 7

#109000
0!
0,

#109500
1!
1,
b1101001 7

#110000
0!
0,

#110500
1!
1,
b1101010 7

#111000
0!
0,

#111500
1!
1,
b1101011 7

#112000
0!
0,

#112500
1!
1,
b1101100 7

#113000
0!
0,

#113500
1!
1,
b1101101 7

#114000
0!
0,

#114500
1!
1,
b1101110 7

#115000
0!
0,

#115500
1!
1,
b1101111 7

#116000
0!
0,

#116500
1!
1,
b1110000 7

#117000
0!
0,

#117500
1!
1,
b1110001 7

#118000
0!
0,

#118500
1!
1,
b1110010 7

#119000
0!
0,

#119500
1!
1,
b1110011 7

#120000
0!
0,

#120500
1!
1,
b1110100 7

#121000
0!
0,

#121500
1!
1,
b1110101 7

#122000
0!
0,

#122500
1!
1,
b1110110 7

#123000
0!
0,

#123500
1!
1,
b1110111 7

#124000
0!
0,

#124500
1!
1,
b1111000 7

#125000
0!
0,

#125500
1!
1,
b1111001 7

#126000
0!
0,

#126500
1!
1,
b1111010 7

#127000
0!
0,

#127500
1!
1,
b1111011 7

#128000
0!
0,

#128500
1!
1,
b1111100 7

#129000
0!
0,

#129500
1!
1,
b1111101 7

#130000
0!
0,

#130500
1!
1,
b1111110 7

#131000
0!
0,

#131500
1!
1,
b1111111 7

#132000
0!
0,

#132500
1!
1,
b10000000 7

#133000
0!
0,

#133500
1!
1,
b10000001 7

#134000
0!
0,

#134500
1!
1,
b10000010 7

#135000
0!
0,

#135500
1!
1,
b10000011 7

#136000
0!
0,

#136500
1!
1,
b10000100 7

#137000
0!
0,

#137500
1!
1,
b10000101 7

#138000
0!
0,

#138500
1!
1,
b10000110 7

#139000
0!
0,

#139500
1!
1,
b10000111 7

#140000
0!
0,

#140500
1!
1,
b10001000 7

#141000
0!
0,

#141500
1!
1,
b10001001 7

#142000
0!
0,

#142500
1!
1,
b10001010 7

#143000
0!
0,

#143500
1!
1,
b10001011 7

#144000
0!
0,

#144500
1!
1,
b10001100 7

#145000
0!
0,

#145500
1!
1,
b10001101 7

#146000
0!
0,

#146500
1!
1,
b10001110 7

#147000
0!
0,

#147500
1!
1,
b10001111 7

#148000
0!
0,

#148500
1!
1,
b10010000 7

#149000
0!
0,

#149500
1!
1,
b10010001 7

#150000
0!
0,

#150500
1!
1,
b10010010 7

#151000
0!
0,

#151500
1!
1,
b10010011 7

#152000
0!
0,

#152500
1!
1,
b10010100 7

#153000
0!
0,

#153500
1!
1,
b10010101 7

#154000
0!
0,

#154500
1!
1,
b10010110 7

#155000
0!
0,

#155500
1!
1,
b10010111 7

#156000
0!
0,

#156500
1!
1,
b10011000 7

#157000
0!
0,

#157500
1!
1,
b10011001 7

#158000
0!
0,

#158500
1!
1,
b10011010 7

#159000
0!
0,

#159500
1!
1,
b10011011 7

#160000
0!
0,

#160500
1!
1,
b10011100 7

#161000
0!
0,

#161500
1!
1,
b10011101 7

#162000
0!
0,

#162500
1!
1,
b10011110 7

#163000
0!
0,

#163500
1!
1,
b10011111 7

#164000
0!
0,

#164500
1!
1,
b10100000 7

#165000
0!
0,

#165500
1!
1,
b10100001 7

#166000
0!
0,

#166500
1!
1,
b10100010 7

#167000
0!
0,

#167500
1!
1,
b10100011 7

#168000
0!
0,

#168500
1!
1,
b10100100 7

#169000
0!
0,

#169500
1!
1,
b10100101 7

#170000
0!
0,

#170500
1!
1,
b10100110 7

#171000
0!
0,

#171500
1!
1,
b10100111 7

#172000
0!
0,

#172500
1!
1,
b10101000 7

#173000
0!
0,

#173500
1!
1,
b10101001 7

#174000
0!
0,

#174500
1!
1,
b10101010 7

#175000
0!
0,

#175500
1!
1,
b10101011 7

#176000
0!
0,

#176500
1!
1,
b10101100 7

#177000
0!
0,

#177500
1!
1,
b10101101 7

#178000
0!
0,

#178500
1!
1,
b10101110 7

#179000
0!
0,

#179500
1!
1,
b10101111 7

#180000
0!
0,

#180500
1!
1,
b10110000 7

#181000
0!
0,

#181500
1!
1,
b10110001 7

#182000
0!
0,

#182500
1!
1,
b10110010 7

#183000
0!
0,

#183500
1!
1,
b10110011 7

#184000
0!
0,

#184500
1!
1,
b10110100 7

#185000
0!
0,

#185500
1!
1,
b10110101 7

#186000
0!
0,

#186500
1!
1,
b10110110 7

#187000
0!
0,

#187500
1!
1,
b10110111 7

#188000
0!
0,

#188500
1!
1,
b10111000 7

#189000
0!
0,

#189500
1!
1,
b10111001 7

#190000
0!
0,

#190500
1!
1,
b10111010 7

#191000
0!
0,

#191500
1!
1,
b10111011 7

#192000
0!
0,

#192500
1!
1,
b10111100 7

#193000
0!
0,

#193500
1!
1,
b10111101 7

#194000
0!
0,

#194500
1!
1,
b10111110 7

#195000
0!
0,

#195500
1!
1,
b10111111 7

#196000
0!
0,

#196500
1!
1,
b11000000 7

#197000
0!
0,

#197500
1!
1,
b11000001 7

#198000
0!
0,

#198500
1!
1,
b11000010 7

#199000
0!
0,

#199500
1!
1,
b11000011 7

#200000
0!
0,

#200500
1!
1,
b11000100 7

#201000
0!
0,

#201500
1!
1,
b11000101 7

#202000
0!
0,

#202500
1!
1,
b11000110 7

#203000
0!
0,

#203500
1!
1,
b11000111 7

#204000
0!
0,

#204500
1!
1,
b11001000 7

#205000
0!
0,

#205500
1!
1,
b11001001 7

#206000
0!
0,

#206500
1!
1,
b11001010 7

#207000
0!
0,

#207500
1!
1,
b11001011 7

#208000
0!
0,

#208500
1!
1,
b11001100 7

#209000
0!
0,

#209500
1!
1,
b11001101 7

#210000
0!
0,

#210500
1!
1,
b11001110 7

#211000
0!
0,

#211500
1!
1,
b11001111 7

#212000
0!
0,

#212500
1!
1,
b11010000 7

#213000
0!
0,

#213500
1!
1,
b11010001 7

#214000
0!
0,

#214500
1!
1,
b11010010 7

#215000
0!
0,

#215500
1!
1,
b11010011 7

#216000
0!
0,

#216500
1!
1,
b11010100 7

#217000
0!
0,

#217500
1!
1,
b11010101 7

#218000
0!
0,

#218500
1!
1,
b11010110 7

#219000
0!
0,

#219500
1!
1,
b11010111 7

#220000
0!
0,

#220500
1!
1,
b11011000 7

#221000
0!
0,

#221500
1!
1,
b11011001 7

#222000
0!
0,

#222500
1!
1,
b11011010 7

#223000
0!
0,

#223500
1!
1,
b11011011 7

#224000
0!
0,

#224500
1!
1,
b11011100 7

#225000
0!
0,

#225500
1!
1,
b11011101 7

#226000
0!
0,

#226500
1!
1,
b11011110 7

#227000
0!
0,

#227500
1!
1,
b11011111 7

#228000
0!
0,

#228500
1!
1,
b11100000 7

#229000
0!
0,

#229500
1!
1,
b11100001 7

#230000
0!
0,

#230500
1!
1,
b11100010 7

#231000
0!
0,

#231500
1!
1,
b11100011 7

#232000
0!
0,

#232500
1!
1,
b11100100 7

#233000
0!
0,

#233500
1!
1,
b11100101 7

#234000
0!
0,

#234500
1!
1,
b11100110 7

#235000
0!
0,

#235500
1!
1,
b11100111 7

#236000
0!
0,

#236500
1!
1,
b11101000 7

#237000
0!
0,

#237500
1!
1,
b11101001 7

#238000
0!
0,

#238500
1!
1,
b11101010 7

#239000
0!
0,

#239500
1!
1,
b11101011 7

#240000
0!
0,

#240500
1!
1,
b11101100 7

#241000
0!
0,

#241500
1!
1,
b11101101 7

#242000
0!
0,

#242500
1!
1,
b11101110 7

#243000
0!
0,

#243500
1!
1,
b11101111 7

#244000
0!
0,

#244500
1!
1,
b11110000 7

#245000
0!
0,

#245500
1!
1,
b11110001 7

#246000
0!
0,

#246500
1!
1,
b11110010 7

#247000
0!
0,

#247500
1!
1,
b11110011 7

#248000
0!
0,

#248500
1!
1,
b11110100 7

#249000
0!
0,

#249500
1!
1,
b11110101 7

#250000
0!
0,

#250500
1!
1,
b11110110 7

#251000
0!
0,

#251500
1!
1,
b11110111 7

#252000
0!
0,

#252500
1!
1,
b11111000 7

#253000
0!
0,

#253500
1!
1,
b11111001 7

#254000
0!
0,

#254500
1!
1,
b11111010 7

#255000
0!
0,

#255500
1!
1,
b11111011 7

#256000
0!
0,

#256500
1!
1,
b11111100 7

#257000
0!
0,

#257500
1!
1,
b11111101 7

#258000
0!
0,

#258500
1!
1,
b11111110 7

#259000
0!
0,

#259500
1!
1,
b11111111 7

#260000
0!
0,

#260500
1!
1,
b100000000 7

#261000
0!
0,

#261500
1!
1,
b100000001 7

#262000
0!
0,

#262500
1!
1,
b100000010 7

#263000
0!
0,

#263500
1!
1,
b100000011 7

#264000
0!
0,

#264500
1!
1,
b100000100 7

#265000
0!
0,

#265500
1!
1,
b100000101 7

#266000
0!
0,

#266500
1!
1,
b100000110 7

#267000
0!
0,

#267500
1!
1,
b100000111 7

#268000
0!
0,

#268500
1!
1,
b100001000 7

#269000
0!
0,

#269500
1!
1,
b100001001 7

#270000
0!
0,

#270500
1!
1,
b100001010 7

#271000
0!
0,

#271500
1!
1,
b100001011 7

#272000
0!
0,

#272500
1!
1,
b100001100 7

#273000
0!
0,

#273500
1!
1,
b100001101 7

#274000
0!
0,

#274500
1!
1,
b100001110 7

#275000
0!
0,

#275500
1!
1,
b100001111 7

#276000
0!
0,

#276500
1!
1,
b100010000 7

#277000
0!
0,

#277500
1!
1,
b100010001 7

#278000
0!
0,

#278500
1!
1,
b100010010 7

#279000
0!
0,

#279500
1!
1,
b100010011 7

#280000
0!
0,

#280500
1!
1,
b100010100 7

#281000
0!
0,

#281500
1!
1,
b100010101 7

#282000
0!
0,

#282500
1!
1,
b100010110 7

#283000
0!
0,

#283500
1!
1,
b100010111 7

#284000
0!
0,

#284500
1!
1,
b100011000 7

#285000
0!
0,

#285500
1!
1,
b100011001 7

#286000
0!
0,

#286500
1!
1,
b100011010 7

#287000
0!
0,

#287500
1!
1,
b100011011 7

#288000
0!
0,

#288500
1!
1,
b100011100 7

#289000
0!
0,

#289500
1!
1,
b100011101 7

#290000
0!
0,

#290500
1!
1,
b100011110 7

#291000
0!
0,

#291500
1!
1,
b100011111 7

#292000
0!
0,

#292500
1!
1,
b100100000 7

#293000
0!
0,

#293500
1!
1,
b100100001 7

#294000
0!
0,

#294500
1!
1,
b100100010 7

#295000
0!
0,

#295500
1!
1,
b100100011 7

#296000
0!
0,

#296500
1!
1,
b100100100 7

#297000
0!
0,

#297500
1!
1,
b100100101 7

#298000
0!
0,

#298500
1!
1,
b100100110 7

#299000
0!
0,

#299500
1!
1,
b100100111 7

#300000
0!
0,

#300500
1!
1,
b100101000 7

#301000
0!
0,

#301500
1!
1,
b100101001 7

#302000
0!
0,

#302500
1!
1,
b100101010 7

#303000
0!
0,

#303500
1!
1,
b100101011 7

#304000
0!
0,

#304500
1!
1,
b100101100 7

#305000
0!
0,

#305500
1!
1,
b100101101 7

#306000
0!
0,

#306500
1!
1,
b100101110 7

#307000
0!
0,

#307500
1!
1,
b100101111 7

#308000
0!
0,

#308500
1!
1,
b100110000 7

#309000
0!
0,

#309500
1!
1,
b100110001 7

#310000
0!
0,

#310500
1!
1,
b100110010 7

#311000
0!
0,

#311500
1!
1,
b100110011 7

#312000
0!
0,

#312500
1!
1,
b100110100 7

#313000
0!
0,

#313500
1!
1,
b100110101 7

#314000
0!
0,

#314500
1!
1,
b100110110 7

#315000
0!
0,

#315500
1!
1,
b100110111 7

#316000
0!
0,

#316500
1!
1,
b100111000 7

#317000
0!
0,

#317500
1!
1,
b100111001 7

#318000
0!
0,

#318500
1!
1,
b100111010 7

#319000
0!
0,

#319500
1!
1,
b100111011 7

#320000
0!
0,

#320500
1!
1,
b100111100 7

#321000
0!
0,

#321500
1!
1,
b100111101 7

#322000
0!
0,

#322500
1!
1,
b100111110 7

#323000
0!
0,

#323500
1!
1,
b100111111 7

#324000
0!
0,

#324500
1!
1,
b101000000 7

#325000
0!
0,

#325500
1!
1,
b101000001 7

#326000
0!
0,

#326500
1!
1,
b101000010 7

#327000
0!
0,

#327500
1!
1,
b101000011 7

#328000
0!
0,

#328500
1!
1,
b101000100 7

#329000
0!
0,

#329500
1!
1,
b101000101 7

#330000
0!
0,

#330500
1!
1,
b101000110 7

#331000
0!
0,

#331500
1!
1,
b101000111 7

#332000
0!
0,

#332500
1!
1,
b101001000 7

#333000
0!
0,

#333500
1!
1,
b101001001 7

#334000
0!
0,

#334500
1!
1,
b101001010 7

#335000
0!
0,

#335500
1!
1,
b101001011 7

#336000
0!
0,

#336500
1!
1,
b101001100 7

#337000
0!
0,

#337500
1!
1,
b101001101 7

#338000
0!
0,

#338500
1!
1,
b101001110 7

#339000
0!
0,

#339500
1!
1,
b101001111 7

#340000
0!
0,

#340500
1!
1,
b101010000 7

#341000
0!
0,

#341500
1!
1,
b101010001 7

#342000
0!
0,

#342500
1!
1,
b101010010 7

#343000
0!
0,

#343500
1!
1,
b101010011 7

#344000
0!
0,

#344500
1!
1,
b101010100 7

#345000
0!
0,

#345500
1!
1,
b101010101 7

#346000
0!
0,

#346500
1!
1,
b101010110 7

#347000
0!
0,

#347500
1!
1,
b101010111 7

#348000
0!
0,

#348500
1!
1,
b101011000 7

#349000
0!
0,

#349500
1!
1,
b101011001 7

#350000
0!
0,

#350500
1!
1,
b101011010 7

#351000
0!
0,

#351500
1!
1,
b101011011 7

#352000
0!
0,

#352500
1!
1,
b101011100 7

#353000
0!
0,

#353500
1!
1,
b101011101 7

#354000
0!
0,

#354500
1!
1,
b101011110 7

#355000
0!
0,

#355500
1!
1,
b101011111 7

#356000
0!
0,

#356500
1!
1,
b101100000 7

#357000
0!
0,

#357500
1!
1,
b101100001 7

#358000
0!
0,

#358500
1!
1,
b101100010 7

#359000
0!
0,

#359500
1!
1,
b101100011 7

#360000
0!
0,

#360500
1!
1,
b101100100 7

#361000
0!
0,

#361500
1!
1,
b101100101 7

#362000
0!
0,

#362500
1!
1,
b101100110 7

#363000
0!
0,

#363500
1!
1,
b101100111 7

#364000
0!
0,

#364500
1!
1,
b101101000 7

#365000
0!
0,

#365500
1!
1,
b101101001 7

#366000
0!
0,

#366500
1!
1,
b101101010 7

#367000
0!
0,

#367500
1!
1,
b101101011 7

#368000
0!
0,

#368500
1!
1,
b101101100 7

#369000
0!
0,

#369500
1!
1,
b101101101 7

#370000
0!
0,

#370500
1!
1,
b101101110 7

#371000
0!
0,

#371500
1!
1,
b101101111 7

#372000
0!
0,

#372500
1!
1,
b101110000 7

#373000
0!
0,

#373500
1!
1,
b101110001 7

#374000
0!
0,

#374500
1!
1,
b101110010 7

#375000
0!
0,

#375500
1!
1,
b101110011 7

#376000
0!
0,

#376500
1!
1,
b101110100 7

#377000
0!
0,

#377500
1!
1,
b101110101 7

#378000
0!
0,

#378500
1!
1,
b101110110 7

#379000
0!
0,

#379500
1!
1,
b101110111 7

#380000
0!
0,

#380500
1!
1,
b101111000 7

#381000
0!
0,

#381500
1!
1,
b101111001 7

#382000
0!
0,

#382500
1!
1,
b101111010 7

#383000
0!
0,

#383500
1!
1,
b101111011 7

#384000
0!
0,

#384500
1!
1,
b101111100 7

#385000
0!
0,

#385500
1!
1,
b101111101 7

#386000
0!
0,

#386500
1!
1,
b101111110 7

#387000
0!
0,

#387500
1!
1,
b101111111 7

#388000
0!
0,

#388500
1!
1,
b110000000 7

#389000
0!
0,

#389500
1!
1,
b110000001 7

#390000
0!
0,

#390500
1!
1,
b110000010 7

#391000
0!
0,

#391500
1!
1,
b110000011 7

#392000
0!
0,

#392500
1!
1,
b110000100 7

#393000
0!
0,

#393500
1!
1,
b110000101 7

#394000
0!
0,

#394500
1!
1,
b110000110 7

#395000
0!
0,

#395500
1!
1,
b110000111 7

#396000
0!
0,

#396500
1!
1,
b110001000 7

#397000
0!
0,

#397500
1!
1,
b110001001 7

#398000
0!
0,

#398500
1!
1,
b110001010 7

#399000
0!
0,

#399500
1!
1,
b110001011 7

#400000
0!
0,

#400500
1!
1,
b110001100 7

#401000
0!
0,

#401500
1!
1,
b110001101 7

#402000
0!
0,

#402500
1!
1,
b110001110 7

#403000
0!
0,

#403500
1!
1,
b110001111 7

#404000
0!
0,

#404500
1!
1,
b110010000 7

#405000
0!
0,

#405500
1!
1,
b110010001 7

#406000
0!
0,

#406500
1!
1,
b110010010 7

#407000
0!
0,

#407500
1!
1,
b110010011 7

#408000
0!
0,

#408500
1!
1,
b110010100 7

#409000
0!
0,

#409500
1!
1,
b110010101 7

#410000
0!
0,

#410500
1!
1,
b110010110 7

#411000
0!
0,

#411500
1!
1,
b110010111 7

#412000
0!
0,

#412500
1!
1,
b110011000 7

#413000
0!
0,

#413500
1!
1,
b110011001 7

#414000
0!
0,

#414500
1!
1,
b110011010 7

#415000
0!
0,

#415500
1!
1,
b110011011 7

#416000
0!
0,

#416500
1!
1,
b110011100 7

#417000
0!
0,

#417500
1!
1,
b110011101 7

#418000
0!
0,

#418500
1!
1,
b110011110 7

#419000
0!
0,

#419500
1!
1,
b110011111 7

#420000
0!
0,

#420500
1!
1,
b110100000 7

#421000
0!
0,

#421500
1!
1,
b110100001 7

#422000
0!
0,

#422500
1!
1,
b110100010 7

#423000
0!
0,

#423500
1!
1,
b110100011 7

#424000
0!
0,

#424500
1!
1,
b110100100 7

#425000
0!
0,

#425500
1!
1,
b110100101 7

#426000
0!
0,

#426500
1!
1,
b110100110 7

#427000
0!
0,

#427500
1!
1,
b110100111 7

#428000
0!
0,

#428500
1!
1,
b110101000 7

#429000
0!
0,

#429500
1!
1,
b110101001 7

#430000
0!
0,

#430500
1!
1,
b110101010 7

#431000
0!
0,

#431500
1!
1,
b110101011 7

#432000
0!
0,

#432500
1!
1,
b110101100 7

#433000
0!
0,

